edc_subject_model_wrappers/__init__.py
edc_subject_model_wrappers/appointment_model_wrapper.py
edc_subject_model_wrappers/apps.py
edc_subject_model_wrappers/crf_model_wrapper.py
edc_subject_model_wrappers/models.py
edc_subject_model_wrappers/requisition_model_wrapper.py
edc_subject_model_wrappers/subject_consent_model_wrapper.py
edc_subject_model_wrappers/subject_locator_model_wrapper.py
edc_subject_model_wrappers/subject_refusal_model_wrapper.py
edc_subject_model_wrappers/subject_refusal_model_wrapper_mixin.py
edc_subject_model_wrappers/subject_visit_model_wrapper.py
edc_subject_model_wrappers/tests/__init__.py
edc_subject_model_wrappers/tests/admin.py
edc_subject_model_wrappers/tests/holidays.csv
edc_subject_model_wrappers/tests/models.py
edc_subject_model_wrappers/tests/urls.py
edc_subject_model_wrappers/tests/visit_schedule.py
edc_subject_model_wrappers/tests/etc/user-aes-local.key
edc_subject_model_wrappers/tests/etc/user-aes-restricted.key
edc_subject_model_wrappers/tests/etc/user-rsa-local-private.pem
edc_subject_model_wrappers/tests/etc/user-rsa-local-public.pem
edc_subject_model_wrappers/tests/etc/user-rsa-restricted-private.pem
edc_subject_model_wrappers/tests/etc/user-rsa-restricted-public.pem
edc_subject_model_wrappers/tests/etc/user-salt-local.key
edc_subject_model_wrappers/tests/etc/user-salt-restricted.key
edc_subject_model_wrappers/tests/tests/__init__.py
edc_subject_model_wrappers/tests/tests/test_appointment_model_wrapper.py
edc_subject_model_wrappers/tests/tests/test_subject_visit_model_wrapper.py
edc_subject_model_wrappers-0.3.24.dist-info/AUTHORS
edc_subject_model_wrappers-0.3.24.dist-info/LICENSE
edc_subject_model_wrappers-0.3.24.dist-info/METADATA
edc_subject_model_wrappers-0.3.24.dist-info/WHEEL
edc_subject_model_wrappers-0.3.24.dist-info/top_level.txt
edc_subject_model_wrappers-0.3.24.dist-info/RECORD
